mypackage/__init__.py
mypackage/functions.py
mypackage/greet.py
hppmodule-1.2.dist-info/METADATA
hppmodule-1.2.dist-info/WHEEL
hppmodule-1.2.dist-info/top_level.txt
hppmodule-1.2.dist-info/RECORD
