Metadata-Version: 2.1
Name: hppmodule
Version: 1.2
Summary: Testing installation of Package
Author: Pa Pa
Author-email: htunpa2aung@gmail.com
License: MIT
Requires-Dist: requests
Requires-Dist: flask
